pytest_remotedata/__init__.py
pytest_remotedata/disable_internet.py
pytest_remotedata/plugin.py
pytest_remotedata/version.py
pytest_remotedata-0.4.1.dist-info/LICENSE.rst
pytest_remotedata-0.4.1.dist-info/METADATA
pytest_remotedata-0.4.1.dist-info/WHEEL
pytest_remotedata-0.4.1.dist-info/entry_points.txt
pytest_remotedata-0.4.1.dist-info/top_level.txt
pytest_remotedata-0.4.1.dist-info/RECORD
